gpt_review/__init__.py
gpt_review/__main__.py
gpt_review/_ask.py
gpt_review/_command.py
gpt_review/_git.py
gpt_review/_gpt_cli.py
gpt_review/_llama_index.py
gpt_review/_openai.py
gpt_review/_review.py
gpt_review/constants.py
gpt_review/context.py
gpt_review/main.py
gpt_review/utils.py
gpt_review/prompts/__init__.py
gpt_review/prompts/_prompt.py
gpt_review/prompts/prompt_bug.yaml
gpt_review/prompts/prompt_coverage.yaml
gpt_review/prompts/prompt_summary.yaml
gpt_review/repositories/__init__.py
gpt_review/repositories/_repository.py
gpt_review/repositories/github.py
gpt_review-0.9.5.dist-info/entry_points.txt
gpt_review-0.9.5.dist-info/LICENSE
gpt_review-0.9.5.dist-info/WHEEL
gpt_review-0.9.5.dist-info/METADATA
gpt_review-0.9.5.dist-info/RECORD
