Metadata-Version: 2.1
Name: gpt-review
Version: 0.9.5
Summary: Python Project for reviewing GitHub PRs with Open AI and Chat-GPT.
Author-email: Daniel Ciborowski <dciborow@microsoft.com>
Requires-Python: >=3.8.1
Classifier: Development Status :: 3 - Alpha
Classifier: Intended Audience :: Developers
Classifier: License :: OSI Approved :: MIT License
Classifier: Programming Language :: Python :: 3 :: Only
Classifier: Programming Language :: Python :: 3.8
Classifier: Programming Language :: Python :: 3.9
Classifier: Programming Language :: Python :: 3.10
Classifier: Programming Language :: Python :: 3.11
Requires-Dist: azure-devops
Requires-Dist: azure-functions; python_version <= "3.10"
Requires-Dist: azure-identity
Requires-Dist: azure-keyvault-secrets
Requires-Dist: llama-index>=0.6.0,<=0.6.14
Requires-Dist: httpx
Requires-Dist: GitPython
Requires-Dist: knack
Requires-Dist: openai
Requires-Dist: requests
Requires-Dist: pyyaml
Requires-Dist: typing_extensions; python_version <= "3.10"
Requires-Dist: transformers; python_version <= "3.8"
Requires-Dist: bandit[toml]==1.7.5 ; extra == "test"
Requires-Dist: black==23.3.0 ; extra == "test"
Requires-Dist: cattrs ; extra == "test"
Requires-Dist: docx2txt ; extra == "test"
Requires-Dist: check-manifest==0.49 ; extra == "test"
Requires-Dist: flake8-bugbear==23.6.5 ; extra == "test"
Requires-Dist: flake8-docstrings ; extra == "test"
Requires-Dist: flake8-formatter_junit_xml ; extra == "test"
Requires-Dist: flake8 ; extra == "test"
Requires-Dist: flake8-pyproject ; extra == "test"
Requires-Dist: pre-commit==3.3.3 ; extra == "test"
Requires-Dist: pylint==2.17.4 ; extra == "test"
Requires-Dist: pylint_junit ; extra == "test"
Requires-Dist: pytest-cov>=3.0.0 ; extra == "test"
Requires-Dist: pytest-mock ; extra == "test"
Requires-Dist: pytest-runner ; extra == "test"
Requires-Dist: pytest-xdist ; extra == "test"
Requires-Dist: pytest>=7.2.2 ; extra == "test"
Requires-Dist: pytest-github-actions-annotate-failures ; extra == "test"
Requires-Dist: shellcheck-py==0.9.0.5 ; extra == "test"
Requires-Dist: requests_mock ; extra == "test"
Project-URL: Documentation, https://github.com/dciborow/action-gpt/tree/main#readme
Project-URL: Source, https://github.com/dciborow/action-gpt
Project-URL: Tracker, https://github.com/dciborow/action-gpt/issues
Provides-Extra: test
